jh_config_manager/__init__.py
jh_config_manager/__main__.py
jh_config_manager/manager.py
jh_config_manager/service.py
jh_config_manager-0.0.1.dist-info/METADATA
jh_config_manager-0.0.1.dist-info/WHEEL
jh_config_manager-0.0.1.dist-info/RECORD
