Metadata-Version: 2.3
Name: jh-config-manager
Version: 0.0.1
Summary: Dynamic JupyterHub config manager service.
License: GPL-3.0-only
Keywords: Pitt,CRC,Jupyter,JupyterHub,JupyterLab,Configuration,Manager
Author: Pitt Center for Research Computing and Data
Requires-Python: >=3.9
Classifier: Framework :: Jupyter
Classifier: Framework :: Jupyter :: JupyterLab
Classifier: Intended Audience :: System Administrators
Classifier: License :: OSI Approved :: GNU General Public License v3 (GPLv3)
Classifier: Natural Language :: English
Classifier: Operating System :: OS Independent
Classifier: Programming Language :: Python
Classifier: Programming Language :: Python :: 3
Classifier: Programming Language :: Python :: 3.9
Classifier: Programming Language :: Python :: 3.10
Classifier: Programming Language :: Python :: 3.11
Classifier: Programming Language :: Python :: 3.12
Classifier: Programming Language :: Python :: 3.13
Classifier: Topic :: System :: Systems Administration
Requires-Dist: jupyterhub
Requires-Dist: tornado
Requires-Dist: traitlets
Project-URL: Documentation, https://github.com/pitt-crc/Jupyter-Authenticator
Project-URL: Homepage, https://github.com/pitt-crc/Jupyter-Authenticator
Project-URL: Repository, https://github.com/pitt-crc/Jupyter-Authenticator
